maithong_package/__init__.py
maithong_package/module.py
maithongpackage999-0.12.dist-info/LICENSE.txt
maithongpackage999-0.12.dist-info/METADATA
maithongpackage999-0.12.dist-info/WHEEL
maithongpackage999-0.12.dist-info/top_level.txt
maithongpackage999-0.12.dist-info/RECORD
